shipyard_file_manipulation/__init__.py
shipyard_file_manipulation/cli/compare.py
shipyard_file_manipulation/cli/compress.py
shipyard_file_manipulation/cli/convert.py
shipyard_file_manipulation/cli/decompress.py
shipyard_file_manipulation/core.py
shipyard_file_manipulation/errors.py
shipyard_file_manipulation-0.2.0.dist-info/METADATA
shipyard_file_manipulation-0.2.0.dist-info/WHEEL
shipyard_file_manipulation-0.2.0.dist-info/RECORD
